{
  "project_info": {
    "project_number": "92393059734",
    "project_id": "practicaintermedia-cvf",
    "storage_bucket": "practicaintermedia-cvf.firebasestorage.app"
  },
  "client": [
    {
      "client_info": {
        "mobilesdk_app_id": "1:92393059734:android:65ccbe9c9cecf834ffd9b7",
        "android_client_info": {
          "package_name": "com.example.practica"
        }
      },
      "oauth_client": [],
      "api_key": [
        {
          "current_key": "AIzaSyCle68n3esz5m4Qnk7u0MIXbu5GdSMBQn8"
        }
      ],
      "services": {
        "appinvite_service": {
          "other_platform_oauth_client": []
        }
      }
    }
  ],
  "configuration_version": "1"
}